rtbhouse_sdk/__init__.py
rtbhouse_sdk/_utils.py
rtbhouse_sdk/client.py
rtbhouse_sdk/exceptions.py
rtbhouse_sdk/py.typed
rtbhouse_sdk/schema.py
rtbhouse_sdk-15.0.0.dist-info/LICENSE
rtbhouse_sdk-15.0.0.dist-info/METADATA
rtbhouse_sdk-15.0.0.dist-info/WHEEL
rtbhouse_sdk-15.0.0.dist-info/RECORD
