Metadata-Version: 2.1
Name: rtbhouse-sdk
Version: 15.0.0
Summary: RTB House SDK
Home-page: https://github.com/rtbhouse-apps/rtbhouse-python-sdk
License: BSD License
Author: RTB House Apps Team
Author-email: apps@rtbhouse.com
Requires-Python: >=3.10,<4.0
Classifier: Development Status :: 5 - Production/Stable
Classifier: Intended Audience :: Developers
Classifier: License :: OSI Approved :: BSD License
Classifier: License :: Other/Proprietary License
Classifier: Natural Language :: English
Classifier: Programming Language :: Python
Classifier: Programming Language :: Python :: 3
Classifier: Programming Language :: Python :: 3.10
Classifier: Programming Language :: Python :: 3.11
Classifier: Programming Language :: Python :: 3.12
Classifier: Programming Language :: Python :: 3.13
Requires-Dist: httpx (>=0.28.0,<0.29.0)
Requires-Dist: pydantic (>=1.9,<3.0)
Project-URL: Repository, https://github.com/rtbhouse-apps/rtbhouse-python-sdk
